[
    {
        "info": "開始春季聯賽對戰",
        "value": "start",
        "arguments": []
    },
    {
        "info": "回報春季聯賽結果",
        "value": "submit",
        "arguments": []
    },
    {
        "info": "開始練習賽對戰",
        "value": "scrim",
        "arguments": []
    },
    {
        "info": "指定模式",
        "value": "pickmode",
        "arguments": []
    },
    {
        "info": "指定場地",
        "value": "pickmap",
        "arguments": []
    },
    {
        "info": "指定模式/場地",
        "value": "pickall",
        "arguments": []
    },
    {
        "info": "指令幫助",
        "value": "help",
        "arguments": []
    }
]